pytest_pytestrail/__init__.py
pytest_pytestrail/__version__.py
pytest_pytestrail/_case.py
pytest_pytestrail/_config.py
pytest_pytestrail/_constants.py
pytest_pytestrail/_sender.py
pytest_pytestrail/plugin.py
pytest_pytestrail/pytestrail.py
pytest_pytestrail_internal-0.0.2.dist-info/licenses/LICENSE
pytest_pytestrail_internal-0.0.2.dist-info/METADATA
pytest_pytestrail_internal-0.0.2.dist-info/WHEEL
pytest_pytestrail_internal-0.0.2.dist-info/entry_points.txt
pytest_pytestrail_internal-0.0.2.dist-info/top_level.txt
pytest_pytestrail_internal-0.0.2.dist-info/RECORD
