Metadata-Version: 2.4
Name: pytest-pytestrail-internal
Version: 0.0.2
Summary: Pytest plugin for interaction with TestRail, Pytest plugin for TestRail (internal fork from: https://github.com/tolstislon/pytest-pytestrail with PR #25 fix)
Home-page: https://github.com/taynguyen/pytest-pytestrail
Author: taynguyen
Author-email: quangtay88@gmail.com
License: MIT License
Keywords: testrail,pytest,pytest-testrail,pytest-pytestrail,testrail_api,api
Classifier: Development Status :: 4 - Beta
Classifier: Intended Audience :: Developers
Classifier: License :: OSI Approved :: MIT License
Classifier: Operating System :: OS Independent
Classifier: Framework :: Pytest
Classifier: Environment :: Plugins
Classifier: Programming Language :: Python :: 3.5
Classifier: Programming Language :: Python :: 3.6
Classifier: Programming Language :: Python :: 3.7
Classifier: Programming Language :: Python :: 3.8
Classifier: Programming Language :: Python :: 3.9
Classifier: Programming Language :: Python :: Implementation
Classifier: Programming Language :: Python :: Implementation :: CPython
Classifier: Programming Language :: Python :: Implementation :: PyPy
Classifier: Topic :: Software Development :: Testing
Classifier: Topic :: Software Development :: Quality Assurance
Requires-Python: >=3.5
License-File: LICENSE
Requires-Dist: pytest>=3.8.0
Requires-Dist: testrail-api>=1.8.0
Dynamic: author
Dynamic: author-email
Dynamic: classifier
Dynamic: description
Dynamic: description-content-type
Dynamic: home-page
Dynamic: keywords
Dynamic: license
Dynamic: license-file
Dynamic: requires-dist
Dynamic: requires-python
Dynamic: summary
